pull_webhook/__init__.py
pull_webhook/cli.py
pull_webhook/pull_webhook.py
pull_webhook-0.1.8.dist-info/METADATA
pull_webhook-0.1.8.dist-info/RECORD
pull_webhook-0.1.8.dist-info/WHEEL
pull_webhook-0.1.8.dist-info/entry_points.txt
pull_webhook-0.1.8.dist-info/top_level.txt
