Metadata-Version: 2.1
Name: pull-webhook
Version: 0.1.8
Summary: Pull latest changes from a git remote
Home-page: https://github.com/jacknova/pull-webhook
Author: Dario Iacampo
Author-email: dario@jntstudio.net
License: MIT license
Keywords: pull_webhook
Platform: UNKNOWN
Classifier: Development Status :: 2 - Pre-Alpha
Classifier: Intended Audience :: Developers
Classifier: License :: OSI Approved :: MIT License
Classifier: Natural Language :: English
Classifier: Programming Language :: Python :: 3.6
Requires-Dist: Click (>=6.0)
